MakePdfEasily.py
__init__.py
MakePdfEasily-0.0.34.dist-info/LICENSE
MakePdfEasily-0.0.34.dist-info/METADATA
MakePdfEasily-0.0.34.dist-info/WHEEL
MakePdfEasily-0.0.34.dist-info/top_level.txt
MakePdfEasily-0.0.34.dist-info/RECORD
