Metadata-Version: 2.1
Name: MakePdfEasily
Version: 0.0.34
Author-email: MakePdfEasily <ali0088552211@gmail.com>
License: Copyright (c) 2018 The Python Packaging Authority
Project-URL: Homepage, https://github.com/Ali-Adnan219/MakePdfEasily
Project-URL: Bug Tracker, https://github.com/Ali-Adnan219/MakePdfEasily/issues
Classifier: Programming Language :: Python :: 3
Classifier: License :: OSI Approved :: MIT License
Classifier: Operating System :: OS Independent
Requires-Python: >=3.7
License-File: LICENSE
Requires-Dist: setuptools (>=61.0.0)
Requires-Dist: wheel
Requires-Dist: Pillow
Requires-Dist: PyPDF2
